mic_stream_util/__init__.py
mic_stream_util/cli.py
mic_stream_util/exceptions.py
mic_stream_util/py.typed
mic_stream_util/test.py
mic_stream_util/backends/__init__.py
mic_stream_util/backends/base_backend.py
mic_stream_util/backends/device_info.py
mic_stream_util/backends/pipewire/__init__.py
mic_stream_util/backends/pipewire/pipewire_backend.py
mic_stream_util/backends/sounddevice/__init__.py
mic_stream_util/backends/sounddevice/sounddevice_backend.py
mic_stream_util/cli/__init__.py
mic_stream_util/cli/main.py
mic_stream_util/cli/commands/__init__.py
mic_stream_util/cli/commands/cpu_usage.py
mic_stream_util/cli/commands/device_info.py
mic_stream_util/cli/commands/devices.py
mic_stream_util/cli/commands/latency_test.py
mic_stream_util/cli/commands/loopback.py
mic_stream_util/cli/commands/memory_usage.py
mic_stream_util/cli/commands/monitor.py
mic_stream_util/cli/commands/record.py
mic_stream_util/cli/commands/route.py
mic_stream_util/cli/commands/spectrum.py
mic_stream_util/cli/commands/vad.py
mic_stream_util/cli/commands/vad_debug.py
mic_stream_util/core/__init__.py
mic_stream_util/core/audio_buffer.py
mic_stream_util/core/audio_config.py
mic_stream_util/core/device_manager.py
mic_stream_util/core/microphone_manager.py
mic_stream_util/speech/__init__.py
mic_stream_util/speech/models.py
mic_stream_util/speech/speech_manager.py
mic_stream_util/util/__init__.py
mic_stream_util/util/fuzzy_match.py
mic_stream_util-0.2.3.dist-info/METADATA
mic_stream_util-0.2.3.dist-info/WHEEL
mic_stream_util-0.2.3.dist-info/entry_points.txt
mic_stream_util-0.2.3.dist-info/RECORD
