Metadata-Version: 2.4
Name: mic-stream-util
Version: 0.2.3
Summary: Library for simplifying microphone streaming and VAD.
Project-URL: Homepage, https://github.com/icampus-wildau/mic-stream-util
Project-URL: Repository, https://github.com/icampus-wildau/mic-stream-util
Author-email: Valentin Schroeter Bonk <vasc9380@th-wildau.de>
Requires-Python: >=3.10
Requires-Dist: click-aliases>=1.0.5
Requires-Dist: click>=8.2.1
Requires-Dist: fuzzywuzzy>=0.18.0
Requires-Dist: numpy>=2.2.6
Requires-Dist: psutil>=7.0.0
Requires-Dist: python-levenshtein>=0.27.1
Requires-Dist: rich>=14.0.0
Requires-Dist: sounddevice>=0.5.2
Requires-Dist: soundfile>=0.13.1
Provides-Extra: all
Requires-Dist: silero-vad>=6.0.0; extra == 'all'
Requires-Dist: torch>=2.7.1; extra == 'all'
Provides-Extra: vad
Requires-Dist: silero-vad>=6.0.0; extra == 'vad'
Requires-Dist: torch>=2.7.1; extra == 'vad'
